[
  {
    "time": 0.6786870956420898,
    "type": "click",
    "button": "Button.left",
    "pos": [179, 540]
  },
  {
    "time": 2.211402654647827,
    "type": "keyDown",
    "button": "Key.shift",
    "pos": null
  },
  {
    "time": 2.87318754196167,
    "type": "click",
    "button": "Button.left",
    "pos": [39, 285]
  },
  {
    "time": 3.0689661502838135,
    "type": "click",
    "button": "Button.left",
    "pos": [39, 285]
  },
  {
    "time": 3.623347043991089,
    "type": "click",
    "button": "Button.left",
    "pos": [39, 335]
  },
  {
    "time": 4.095809459686279,
    "type": "click",
    "button": "Button.left",
    "pos": [43, 376]
  },
  {
    "time": 4.583647966384888,
    "type": "click",
    "button": "Button.left",
    "pos": [43, 424]
  },
  {
    "time": 5.280613660812378,
    "type": "click",
    "button": "Button.left",
    "pos": [86, 285]
  },
  {
    "time": 5.475719451904297,
    "type": "click",
    "button": "Button.left",
    "pos": [86, 285]
  },
  {
    "time": 6.015951871871948,
    "type": "click",
    "button": "Button.left",
    "pos": [86, 328]
  },
  {
    "time": 6.593106031417847,
    "type": "click",
    "button": "Button.left",
    "pos": [86, 378]
  },
  {
    "time": 7.147964954376221,
    "type": "click",
    "button": "Button.left",
    "pos": [87, 428]
  },
  {
    "time": 7.800915479660034,
    "type": "click",
    "button": "Button.left",
    "pos": [138, 281]
  },
  {
    "time": 8.011034727096558,
    "type": "click",
    "button": "Button.left",
    "pos": [138, 281]
  },
  {
    "time": 8.656353950500488,
    "type": "click",
    "button": "Button.left",
    "pos": [131, 336]
  },
  {
    "time": 9.188396692276001,
    "type": "click",
    "button": "Button.left",
    "pos": [138, 372]
  },
  {
    "time": 9.758564710617065,
    "type": "click",
    "button": "Button.left",
    "pos": [138, 424]
  },
  {
    "time": 10.485960960388184,
    "type": "click",
    "button": "Button.left",
    "pos": [143, 452]
  },
  {
    "time": 10.876048564910889,
    "type": "click",
    "button": "Button.left",
    "pos": [143, 454]
  },
  {
    "time": 11.250696420669556,
    "type": "click",
    "button": "Button.left",
    "pos": [146, 457]
  },
  {
    "time": 11.896156787872314,
    "type": "click",
    "button": "Button.left",
    "pos": [35, 278]
  },
  {
    "time": 12.142829895019531,
    "type": "click",
    "button": "Button.left",
    "pos": [35, 278]
  },
  {
    "time": 12.630576610565186,
    "type": "click",
    "button": "Button.left",
    "pos": [34, 295]
  },
  {
    "time": 13.133354187011719,
    "type": "click",
    "button": "Button.left",
    "pos": [42, 329]
  },
  {
    "time": 13.688691139221191,
    "type": "click",
    "button": "Button.left",
    "pos": [44, 374]
  },
  {
    "time": 14.2507164478302,
    "type": "click",
    "button": "Button.left",
    "pos": [42, 405]
  },
  {
    "time": 14.993353366851807,
    "type": "click",
    "button": "Button.left",
    "pos": [86, 280]
  },
  {
    "time": 15.173950433731079,
    "type": "click",
    "button": "Button.left",
    "pos": [86, 280]
  },
  {
    "time": 15.84805965423584,
    "type": "click",
    "button": "Button.left",
    "pos": [80, 341]
  },
  {
    "time": 16.38099241256714,
    "type": "click",
    "button": "Button.left",
    "pos": [81, 361]
  },
  {
    "time": 16.95012855529785,
    "type": "click",
    "button": "Button.left",
    "pos": [90, 420]
  },
  {
    "time": 17.618000030517578,
    "type": "click",
    "button": "Button.left",
    "pos": [131, 285]
  },
  {
    "time": 17.797879934310913,
    "type": "click",
    "button": "Button.left",
    "pos": [131, 285]
  },
  {
    "time": 18.413329362869263,
    "type": "click",
    "button": "Button.left",
    "pos": [133, 330]
  },
  {
    "time": 18.961276292800903,
    "type": "click",
    "button": "Button.left",
    "pos": [132, 372]
  },
  {
    "time": 19.478206634521484,
    "type": "click",
    "button": "Button.left",
    "pos": [131, 406]
  },
  {
    "time": 20.115806341171265,
    "type": "click",
    "button": "Button.left",
    "pos": [149, 451]
  },
  {
    "time": 20.73050022125244,
    "type": "click",
    "button": "Button.left",
    "pos": [132, 284]
  },
  {
    "time": 20.918272972106934,
    "type": "click",
    "button": "Button.left",
    "pos": [132, 284]
  },
  {
    "time": 21.525471687316895,
    "type": "click",
    "button": "Button.left",
    "pos": [141, 329]
  },
  {
    "time": 22.043020248413086,
    "type": "click",
    "button": "Button.left",
    "pos": [134, 369]
  },
  {
    "time": 22.613218307495117,
    "type": "click",
    "button": "Button.left",
    "pos": [133, 433]
  },
  {
    "time": 23.611085653305054,
    "type": "click",
    "button": "Button.left",
    "pos": [728, 285]
  },
  {
    "time": 23.798312187194824,
    "type": "click",
    "button": "Button.left",
    "pos": [728, 285]
  },
  {
    "time": 23.99381184577942,
    "type": "click",
    "button": "Button.left",
    "pos": [728, 285]
  },
  {
    "time": 24.203250885009766,
    "type": "click",
    "button": "Button.left",
    "pos": [728, 285]
  },
  {
    "time": 24.398059844970703,
    "type": "click",
    "button": "Button.left",
    "pos": [728, 285]
  },
  {
    "time": 24.608413457870483,
    "type": "click",
    "button": "Button.left",
    "pos": [728, 285]
  },
  {
    "time": 24.818269729614258,
    "type": "click",
    "button": "Button.left",
    "pos": [728, 285]
  },
  {
    "time": 25.02809453010559,
    "type": "click",
    "button": "Button.left",
    "pos": [728, 285]
  },
  {
    "time": 25.238240957260132,
    "type": "click",
    "button": "Button.left",
    "pos": [728, 285]
  },
  {
    "time": 25.456255197525024,
    "type": "click",
    "button": "Button.left",
    "pos": [728, 285]
  },
  {
    "time": 25.68090033531189,
    "type": "click",
    "button": "Button.left",
    "pos": [728, 285]
  },
  {
    "time": 25.891046047210693,
    "type": "click",
    "button": "Button.left",
    "pos": [728, 285]
  },
  {
    "time": 26.11546230316162,
    "type": "click",
    "button": "Button.left",
    "pos": [728, 285]
  },
  {
    "time": 26.333430767059326,
    "type": "click",
    "button": "Button.left",
    "pos": [728, 285]
  },
  {
    "time": 26.550904512405396,
    "type": "click",
    "button": "Button.left",
    "pos": [728, 285]
  },
  {
    "time": 26.761209964752197,
    "type": "click",
    "button": "Button.left",
    "pos": [728, 285]
  },
  {
    "time": 26.98579216003418,
    "type": "click",
    "button": "Button.left",
    "pos": [728, 285]
  },
  {
    "time": 27.211074829101562,
    "type": "click",
    "button": "Button.left",
    "pos": [728, 285]
  },
  {
    "time": 27.435909032821655,
    "type": "click",
    "button": "Button.left",
    "pos": [728, 285]
  },
  {
    "time": 27.653086185455322,
    "type": "click",
    "button": "Button.left",
    "pos": [728, 285]
  },
  {
    "time": 27.871513843536377,
    "type": "click",
    "button": "Button.left",
    "pos": [728, 285]
  },
  {
    "time": 28.08103656768799,
    "type": "click",
    "button": "Button.left",
    "pos": [728, 285]
  },
  {
    "time": 28.306365966796875,
    "type": "click",
    "button": "Button.left",
    "pos": [728, 285]
  },
  {
    "time": 28.52347683906555,
    "type": "click",
    "button": "Button.left",
    "pos": [728, 285]
  },
  {
    "time": 28.74066185951233,
    "type": "click",
    "button": "Button.left",
    "pos": [728, 285]
  },
  {
    "time": 28.958215951919556,
    "type": "click",
    "button": "Button.left",
    "pos": [728, 285]
  },
  {
    "time": 29.168099641799927,
    "type": "click",
    "button": "Button.left",
    "pos": [728, 285]
  },
  {
    "time": 29.40065908432007,
    "type": "click",
    "button": "Button.left",
    "pos": [728, 285]
  },
  {
    "time": 29.626298427581787,
    "type": "click",
    "button": "Button.left",
    "pos": [728, 285]
  },
  {
    "time": 29.851306200027466,
    "type": "click",
    "button": "Button.left",
    "pos": [728, 285]
  },
  {
    "time": 30.053284883499146,
    "type": "click",
    "button": "Button.left",
    "pos": [728, 285]
  },
  {
    "time": 30.285887479782104,
    "type": "click",
    "button": "Button.left",
    "pos": [728, 285]
  },
  {
    "time": 30.495585441589355,
    "type": "click",
    "button": "Button.left",
    "pos": [728, 285]
  },
  {
    "time": 30.713725805282593,
    "type": "click",
    "button": "Button.left",
    "pos": [728, 285]
  },
  {
    "time": 31.201159954071045,
    "type": "keyUp",
    "button": "Key.shift",
    "pos": null
  },
  {
    "time": 32.446126222610474,
    "type": "click",
    "button": "Button.left",
    "pos": [785, 218]
  },
  {
    "time": 33.51053071022034,
    "type": "click",
    "button": "Button.left",
    "pos": [256, 511]
  },
  {
    "time": 33.71053071022034,
    "type": "click",
    "button": "Button.left",
    "pos": [256, 511]
  }
]
